quasar/__init__.py
quasar/finetune.py
quasar/train.py
quasarx-0.0.2.dist-info/LICENSE
quasarx-0.0.2.dist-info/WHEEL
quasarx-0.0.2.dist-info/METADATA
quasarx-0.0.2.dist-info/RECORD
