Metadata-Version: 2.1
Name: quasarx
Version: 0.0.2
Summary: quasar - Pytorch
Home-page: https://github.com/kyegomez/quasar
License: MIT
Keywords: artificial intelligence,deep learning,optimizers,Prompt Engineering
Author: Kye Gomez
Author-email: kye@apac.ai
Requires-Python: >=3.6,<4.0
Classifier: Development Status :: 4 - Beta
Classifier: Intended Audience :: Developers
Classifier: License :: OSI Approved :: MIT License
Classifier: Programming Language :: Python :: 3
Classifier: Programming Language :: Python :: 3.6
Classifier: Programming Language :: Python :: 3.7
Classifier: Programming Language :: Python :: 3.8
Classifier: Programming Language :: Python :: 3.9
Classifier: Programming Language :: Python :: 3.10
Classifier: Programming Language :: Python :: 3.11
Classifier: Programming Language :: Python :: 3.6
Classifier: Topic :: Scientific/Engineering :: Artificial Intelligence
Requires-Dist: accelerate
Requires-Dist: bitsandbytes
Requires-Dist: datasets
Requires-Dist: deepspeed
Requires-Dist: einops
Requires-Dist: evaluate
Requires-Dist: matplotlib
Requires-Dist: numpy
Requires-Dist: pandas
Requires-Dist: peft
Requires-Dist: protobuf
Requires-Dist: scikit-learn
Requires-Dist: sentencepiece
Requires-Dist: torch
Requires-Dist: tqdm
Requires-Dist: transformers
Requires-Dist: trl
Requires-Dist: wandb
Project-URL: Repository, https://github.com/kyegomez/quasar
